woopac2/__init__.py
woopac2/__main__.py
woopac2/app/__init__.py
woopac2/app/app.py
woopac2/utils/__init__.py
woopac2/utils/exceptions.py
woopac2/utils/functions.py
woopac2-1.1.dist-info/LICENSE
woopac2-1.1.dist-info/METADATA
woopac2-1.1.dist-info/WHEEL
woopac2-1.1.dist-info/entry_points.txt
woopac2-1.1.dist-info/top_level.txt
woopac2-1.1.dist-info/RECORD
